soundplay.py
soundplay-1.3.1.dist-info/LICENSE
soundplay-1.3.1.dist-info/METADATA
soundplay-1.3.1.dist-info/WHEEL
soundplay-1.3.1.dist-info/top_level.txt
soundplay-1.3.1.dist-info/RECORD
